crypticorn_utils/__init__.py
crypticorn_utils/ansi_colors.py
crypticorn_utils/auth.py
crypticorn_utils/logging.py
crypticorn_utils/metrics.py
crypticorn_utils/middleware.py
crypticorn_utils/pagination.py
crypticorn_utils/py.typed
crypticorn_utils/types.py
crypticorn_utils/utils.py
crypticorn_utils/warnings.py
crypticorn_utils-3.0.0.dist-info/licenses/LICENSE
crypticorn_utils-3.0.0.dist-info/WHEEL
crypticorn_utils-3.0.0.dist-info/METADATA
crypticorn_utils-3.0.0.dist-info/RECORD
